[
  {
    "key": "ctrl+tab",
    "command": "workbench.action.terminal.focusNext",
    "when": "terminalFocus"
  },
  {
    "key": "shift+tab",
    "command": "workbench.action.terminal.focusPrevious",
    "when": "terminalFocus"
  },
  {
    "key": "alt+enter",
    "command": "workbench.action.togglePanel"
  },
  {
    "key": "ctrl+n",
    "command": "workbench.action.terminal.new",
    "when": "terminalFocus"
  },
  {
    "key": "ctrl+q",
    "command": "workbench.action.terminal.kill",
    "when": "terminalFocus"
  },
  // Toggle between terminal and editor focus
  {
    "key": "ctrl+up",
    "command": "workbench.action.terminal.focus"
  },
  {
    "key": "ctrl+up",
    "command": "workbench.action.focusActiveEditorGroup",
    "when": "terminalFocus"
  },
  {
    "key": "ctrl+down",
    "command": "workbench.action.terminal.focus"
  },
  {
    "key": "ctrl+down",
    "command": "workbench.action.focusActiveEditorGroup",
    "when": "terminalFocus"
  },
  // FILE TREE
  {
    "key": "ctrl+right",
    "command": "workbench.action.focusFirstEditorGroup",
    "when": "explorerViewletVisible && !editorFocus"
  },
  {
    "key": "ctrl+left",
    "command": "workbench.view.explorer"
  },
  {
    "command": "workbench.action.toggleSidebarVisibility",
    "key": "ctrl+e"
  },
  {
    "command": "workbench.files.action.focusFilesExplorer",
    "key": "ctrl+e",
    "when": "editorTextFocus"
  },
  {
    "key": "n",
    "command": "explorer.newFile",
    "when": "filesExplorerFocus && !inputFocus"
  },
  {
    "command": "renameFile",
    "key": "r",
    "when": "filesExplorerFocus && !inputFocus"
  },
  {
    "key": "shift+n",
    "command": "explorer.newFolder",
    "when": "explorerViewletFocus"
  },
  {
    "key": "ctrl+shift+n",
    "command": "workbench.action.newWindow",
    "when": "!explorerViewletFocus"
  },
  {
    "command": "deleteFile",
    "key": "d",
    "when": "filesExplorerFocus && !inputFocus"
  },
  {
    "key": "ctrl+w",
    "command": "workbench.action.closeActiveEditor"
  },
  {
    "key": "ctrl+shift+q",
    "command": "workbench.action.quit"
  },
  {
    "key": "ctrl+w",
    "command": "-workbench.action.quit"
  }
]
